vkit/__init__.py
vkit/element/__init__.py
vkit/element/box.py
vkit/element/image.py
vkit/element/lexicon.py
vkit/element/line.py
vkit/element/mask.py
vkit/element/opt.py
vkit/element/painter.py
vkit/element/point.py
vkit/element/polygon.py
vkit/element/score_map.py
vkit/element/type.py
vkit/element/uniqueness.py
vkit/engine/__init__.py
vkit/engine/interface.py
vkit/engine/char_and_font_sampler/__init__.py
vkit/engine/char_sampler/__init__.py
vkit/engine/char_sampler/corpus.py
vkit/engine/char_sampler/datetime.py
vkit/engine/char_sampler/faker.py
vkit/engine/char_sampler/lexicon.py
vkit/engine/char_sampler/type.py
vkit/engine/distortion/__init__.py
vkit/engine/distortion/interface.py
vkit/engine/distortion/geometric/__init__.py
vkit/engine/distortion/geometric/affine.py
vkit/engine/distortion/geometric/camera.py
vkit/engine/distortion/geometric/mls.py
vkit/engine/distortion/geometric/grid_rendering/__init__.py
vkit/engine/distortion/geometric/grid_rendering/grid_blender.py
vkit/engine/distortion/geometric/grid_rendering/grid_creator.py
vkit/engine/distortion/geometric/grid_rendering/interface.py
vkit/engine/distortion/geometric/grid_rendering/point_projector.py
vkit/engine/distortion/geometric/grid_rendering/type.py
vkit/engine/distortion/geometric/grid_rendering/visualization.py
vkit/engine/distortion/photometric/__init__.py
vkit/engine/distortion/photometric/blur.py
vkit/engine/distortion/photometric/color.py
vkit/engine/distortion/photometric/effect.py
vkit/engine/distortion/photometric/noise.py
vkit/engine/distortion/photometric/opt.py
vkit/engine/distortion/photometric/streak.py
vkit/engine/distortion_policy/__init__.py
vkit/engine/distortion_policy/opt.py
vkit/engine/distortion_policy/random_distortion.py
vkit/engine/distortion_policy/type.py
vkit/engine/distortion_policy/geometric/__init__.py
vkit/engine/distortion_policy/geometric/affine.py
vkit/engine/distortion_policy/geometric/camera.py
vkit/engine/distortion_policy/geometric/mls.py
vkit_nightly-22.723.1123.dist-info/LICENSE.txt
vkit_nightly-22.723.1123.dist-info/LICENSE_COMMERCIAL.txt
vkit_nightly-22.723.1123.dist-info/LICENSE_OSS.txt
vkit_nightly-22.723.1123.dist-info/METADATA
vkit_nightly-22.723.1123.dist-info/WHEEL
vkit_nightly-22.723.1123.dist-info/top_level.txt
vkit_nightly-22.723.1123.dist-info/RECORD
